{"sections":{"main":{"type":"main-product","blocks":{"title":{"type":"title","settings":{}},"price":{"type":"price","settings":{}},"variant_picker":{"type":"variant_picker","settings":{}},"quantity_selector":{"type":"quantity_selector","settings":{}},"buy_buttons":{"type":"buy_buttons","settings":{}},"description":{"type":"description","settings":{}},"share":{"type":"share","settings":{}}},"block_order":["title","price","variant_picker","buy_buttons","description","share"],"settings":{}}},"order":["main"]}